HTTPserver_mock.py
HTTPserver_mock-2.dist-info/METADATA
HTTPserver_mock-2.dist-info/WHEEL
HTTPserver_mock-2.dist-info/top_level.txt
HTTPserver_mock-2.dist-info/RECORD
